pyaudio-stubs/METADATA.toml
pyaudio-stubs/__init__.pyi
pyaudio-stubs/py.typed
types_pyaudio-0.2.16.20240425.dist-info/METADATA
types_pyaudio-0.2.16.20240425.dist-info/WHEEL
types_pyaudio-0.2.16.20240425.dist-info/top_level.txt
types_pyaudio-0.2.16.20240425.dist-info/RECORD
